[
  {
    "id": 2119892,
    "title": "clickjacing can lead to account takeover",
    "url": "https://hackerone.com/reports/2119892",
    "substate": "resolved",
    "severity_rating": "Low",
    "disclosed": true,
    "disclosed_at": "2026-01-18T11:21:37.695Z",
    "submitted_at": "2023-08-22T17:07:42.485Z",
    "cve_ids": [],
    "cwe": "UI Redressing (Clickjacking)",
    "votes": 68,
    "total_awarded_amount": 200,
    "reporter": "hyk3n",
    "program": "pixiv",
    "program_name": "pixiv"
  },
  {
    "id": 1031525,
    "title": "User Impersonation through sendMessage options",
    "url": "https://hackerone.com/reports/1031525",
    "substate": "resolved",
    "severity_rating": "Medium",
    "disclosed": true,
    "disclosed_at": "2024-08-10T21:58:02.682Z",
    "submitted_at": "2020-11-11T11:26:35.150Z",
    "cve_ids": [],
    "cwe": "UI Redressing (Clickjacking)",
    "votes": 5,
    "total_awarded_amount": null,
    "reporter": "gronke",
    "program": "rocket_chat",
    "program_name": "Rocket.Chat"
  },
  {
    "id": 1416612,
    "title": "Clickjacking Vulnerability Can Leads To Delete Developer APP",
    "url": "https://hackerone.com/reports/1416612",
    "substate": "resolved",
    "severity_rating": "Low",
    "disclosed": true,
    "disclosed_at": "2022-05-04T22:25:51.239Z",
    "submitted_at": "2021-12-04T07:07:40.366Z",
    "cve_ids": [],
    "cwe": "UI Redressing (Clickjacking)",
    "votes": 26,
    "total_awarded_amount": 500,
    "reporter": "rioncool22",
    "program": "tiktok",
    "program_name": "TikTok"
  },
  {
    "id": 783191,
    "title": "Clickjacking to change email address",
    "url": "https://hackerone.com/reports/783191",
    "substate": "resolved",
    "severity_rating": "High",
    "disclosed": true,
    "disclosed_at": "2022-01-12T08:33:43.087Z",
    "submitted_at": "2020-01-25T14:00:26.294Z",
    "cve_ids": [],
    "cwe": "UI Redressing (Clickjacking)",
    "votes": 7,
    "total_awarded_amount": null,
    "reporter": "paramdham",
    "program": "gener8",
    "program_name": "Gener8"
  },
  {
    "id": 1294767,
    "title": "clickjacking on deleting user's clips [https://crossclip.com/clips]",
    "url": "https://hackerone.com/reports/1294767",
    "substate": "resolved",
    "severity_rating": "Low",
    "disclosed": true,
    "disclosed_at": "2021-11-05T20:39:29.102Z",
    "submitted_at": "2021-08-08T00:02:21.717Z",
    "cve_ids": [],
    "cwe": "UI Redressing (Clickjacking)",
    "votes": 4,
    "total_awarded_amount": null,
    "reporter": "ibrahimatix0x01",
    "program": "logitech",
    "program_name": "Logitech"
  },
  {
    "id": 305128,
    "title": "ClickJacking on IMPORTANT Functions of Yelp",
    "url": "https://hackerone.com/reports/305128",
    "substate": "resolved",
    "severity_rating": "Low",
    "disclosed": true,
    "disclosed_at": "2020-08-21T20:41:41.078Z",
    "submitted_at": "2018-01-16T07:45:07.301Z",
    "cve_ids": [],
    "cwe": "UI Redressing (Clickjacking)",
    "votes": 5,
    "total_awarded_amount": null,
    "reporter": "hk755a",
    "program": "yelp",
    "program_name": "Yelp"
  },
  {
    "id": 765355,
    "title": "Modify account details by exploiting clickjacking vulnerability on refer.wordpress.com",
    "url": "https://hackerone.com/reports/765355",
    "substate": "resolved",
    "severity_rating": "Low",
    "disclosed": true,
    "disclosed_at": "2020-02-22T16:02:07.318Z",
    "submitted_at": "2019-12-28T05:44:47.958Z",
    "cve_ids": [],
    "cwe": "UI Redressing (Clickjacking)",
    "votes": 12,
    "total_awarded_amount": null,
    "reporter": "theamanrawat",
    "program": "automattic",
    "program_name": "Automattic"
  },
  {
    "id": 662287,
    "title": "Cross-site Scripting (XSS) - Stored in RDoc wiki pages",
    "url": "https://hackerone.com/reports/662287",
    "substate": "resolved",
    "severity_rating": "High",
    "disclosed": true,
    "disclosed_at": "2019-12-16T09:02:35.750Z",
    "submitted_at": "2019-07-28T15:31:34.731Z",
    "cve_ids": [],
    "cwe": "UI Redressing (Clickjacking)",
    "votes": 282,
    "total_awarded_amount": 3500,
    "reporter": "vakzz",
    "program": "gitlab",
    "program_name": "GitLab"
  },
  {
    "id": 643274,
    "title": "Viral Direct Message Clickjacking via link truncation leading to capture of both Google credentials & installation of malicious 3rd party Twitter App",
    "url": "https://hackerone.com/reports/643274",
    "substate": "resolved",
    "severity_rating": "High",
    "disclosed": true,
    "disclosed_at": "2019-10-31T17:12:30.365Z",
    "submitted_at": "2019-07-15T08:48:09.118Z",
    "cve_ids": [],
    "cwe": "UI Redressing (Clickjacking)",
    "votes": 64,
    "total_awarded_amount": null,
    "reporter": "slickrockweb",
    "program": "x",
    "program_name": "X / xAI"
  },
  {
    "id": 463695,
    "title": "Certificate warnings and similar UI elements in Web protection of Anti-Virus products family are susceptible to clickjacking",
    "url": "https://hackerone.com/reports/463695",
    "substate": "resolved",
    "severity_rating": "Medium",
    "disclosed": true,
    "disclosed_at": "2019-08-28T17:54:56.804Z",
    "submitted_at": "2018-12-17T10:02:35.319Z",
    "cve_ids": [],
    "cwe": "UI Redressing (Clickjacking)",
    "votes": 11,
    "total_awarded_amount": null,
    "reporter": "palant",
    "program": "kaspersky",
    "program_name": "Kaspersky"
  },
  {
    "id": 591432,
    "title": "Twitter Periscope Clickjacking Vulnerability",
    "url": "https://hackerone.com/reports/591432",
    "substate": "resolved",
    "severity_rating": "Medium",
    "disclosed": true,
    "disclosed_at": "2019-07-10T06:00:48.053Z",
    "submitted_at": "2019-05-28T11:59:05.165Z",
    "cve_ids": [],
    "cwe": "UI Redressing (Clickjacking)",
    "votes": 140,
    "total_awarded_amount": 1120,
    "reporter": "eo420",
    "program": "x",
    "program_name": "X / xAI"
  },
  {
    "id": 223024,
    "title": "Clickjacking In jobs.wordpress.net",
    "url": "https://hackerone.com/reports/223024",
    "substate": "resolved",
    "severity_rating": "Low",
    "disclosed": true,
    "disclosed_at": "2018-08-22T14:40:11.571Z",
    "submitted_at": "2017-04-22T10:24:33.914Z",
    "cve_ids": [],
    "cwe": "UI Redressing (Clickjacking)",
    "votes": 16,
    "total_awarded_amount": null,
    "reporter": "zeeshan_waheed",
    "program": "wordpress",
    "program_name": "WordPress"
  },
  {
    "id": 85624,
    "title": "Highly wormable clickjacking in player card",
    "url": "https://hackerone.com/reports/85624",
    "substate": "resolved",
    "severity_rating": null,
    "disclosed": true,
    "disclosed_at": "2018-05-17T23:11:28.495Z",
    "submitted_at": "2015-08-30T06:43:37.878Z",
    "cve_ids": [],
    "cwe": "UI Redressing (Clickjacking)",
    "votes": 134,
    "total_awarded_amount": null,
    "reporter": "filedescriptor",
    "program": "x",
    "program_name": "X / xAI"
  },
  {
    "id": 298028,
    "title": "Clickjacking on https://www.goodhire.com/api",
    "url": "https://hackerone.com/reports/298028",
    "substate": "resolved",
    "severity_rating": "Low",
    "disclosed": true,
    "disclosed_at": "2018-05-10T01:12:02.597Z",
    "submitted_at": "2017-12-14T20:22:06.893Z",
    "cve_ids": [],
    "cwe": "UI Redressing (Clickjacking)",
    "votes": 12,
    "total_awarded_amount": null,
    "reporter": "tolo7010",
    "program": "inflection",
    "program_name": "Inflection"
  },
  {
    "id": 299009,
    "title": "Single Sing On - Clickjacking",
    "url": "https://hackerone.com/reports/299009",
    "substate": "resolved",
    "severity_rating": "Low",
    "disclosed": true,
    "disclosed_at": "2018-02-21T15:27:13.238Z",
    "submitted_at": "2017-12-18T05:11:32.852Z",
    "cve_ids": [],
    "cwe": "UI Redressing (Clickjacking)",
    "votes": 11,
    "total_awarded_amount": null,
    "reporter": "r0p3",
    "program": "semrush",
    "program_name": "Semrush"
  },
  {
    "id": 289246,
    "title": "Following links are vulnerable to clickjacking",
    "url": "https://hackerone.com/reports/289246",
    "substate": "resolved",
    "severity_rating": "Low",
    "disclosed": true,
    "disclosed_at": "2018-01-11T09:47:45.261Z",
    "submitted_at": "2017-11-10T18:29:40.983Z",
    "cve_ids": [],
    "cwe": "UI Redressing (Clickjacking)",
    "votes": 12,
    "total_awarded_amount": null,
    "reporter": "karma1",
    "program": "semrush",
    "program_name": "Semrush"
  },
  {
    "id": 291683,
    "title": "Crafted frame injection leading to form-based UI redressing.",
    "url": "https://hackerone.com/reports/291683",
    "substate": "resolved",
    "severity_rating": null,
    "disclosed": true,
    "disclosed_at": "2017-12-31T17:04:02.871Z",
    "submitted_at": "2017-11-19T10:13:33.854Z",
    "cve_ids": [],
    "cwe": "UI Redressing (Clickjacking)",
    "votes": 14,
    "total_awarded_amount": null,
    "reporter": "edoverflow",
    "program": "automattic",
    "program_name": "Automattic"
  },
  {
    "id": 270454,
    "title": "Clickjacking in Legalrobot app",
    "url": "https://hackerone.com/reports/270454",
    "substate": "resolved",
    "severity_rating": null,
    "disclosed": true,
    "disclosed_at": "2017-11-10T11:36:03.466Z",
    "submitted_at": "2017-09-22T07:04:48.244Z",
    "cve_ids": [],
    "cwe": "UI Redressing (Clickjacking)",
    "votes": 8,
    "total_awarded_amount": null,
    "reporter": "9it0wl",
    "program": "legalrobot",
    "program_name": "Legal Robot"
  },
  {
    "id": 258283,
    "title": "Clickjacking - https://mercantile.wordpress.org/",
    "url": "https://hackerone.com/reports/258283",
    "substate": "resolved",
    "severity_rating": "Low",
    "disclosed": true,
    "disclosed_at": "2017-08-28T17:11:41.615Z",
    "submitted_at": "2017-08-09T15:05:27.500Z",
    "cve_ids": [],
    "cwe": "UI Redressing (Clickjacking)",
    "votes": 8,
    "total_awarded_amount": null,
    "reporter": "giantfire",
    "program": "wordpress",
    "program_name": "WordPress"
  },
  {
    "id": 244697,
    "title": "UI Redressing on Embedded Charts",
    "url": "https://hackerone.com/reports/244697",
    "substate": "resolved",
    "severity_rating": "Low",
    "disclosed": true,
    "disclosed_at": "2017-07-05T06:23:20.688Z",
    "submitted_at": "2017-06-30T10:35:04.706Z",
    "cve_ids": [],
    "cwe": "UI Redressing (Clickjacking)",
    "votes": 6,
    "total_awarded_amount": null,
    "reporter": "mr_r3boot",
    "program": "wakatime",
    "program_name": "WakaTime"
  },
  {
    "id": 244967,
    "title": "Clickjacking on authorized page https://wakatime.com/share/embed",
    "url": "https://hackerone.com/reports/244967",
    "substate": "resolved",
    "severity_rating": "Low",
    "disclosed": true,
    "disclosed_at": "2017-07-05T06:21:31.084Z",
    "submitted_at": "2017-07-01T02:53:51.505Z",
    "cve_ids": [],
    "cwe": "UI Redressing (Clickjacking)",
    "votes": 8,
    "total_awarded_amount": null,
    "reporter": "silv3rpoision",
    "program": "wakatime",
    "program_name": "WakaTime"
  },
  {
    "id": 225555,
    "title": "ClickJacking on Debug",
    "url": "https://hackerone.com/reports/225555",
    "substate": "resolved",
    "severity_rating": null,
    "disclosed": true,
    "disclosed_at": "2017-06-16T14:11:47.714Z",
    "submitted_at": "2017-05-02T13:59:23.523Z",
    "cve_ids": [],
    "cwe": "UI Redressing (Clickjacking)",
    "votes": 2,
    "total_awarded_amount": null,
    "reporter": "bf7e43565d8cf54de3bc5a7",
    "program": "weblate",
    "program_name": "Weblate"
  },
  {
    "id": 234713,
    "title": "Clickjacking on Mixmax.com",
    "url": "https://hackerone.com/reports/234713",
    "substate": "resolved",
    "severity_rating": "High",
    "disclosed": true,
    "disclosed_at": "2017-06-13T05:54:44.911Z",
    "submitted_at": "2017-05-31T04:47:36.326Z",
    "cve_ids": [],
    "cwe": "UI Redressing (Clickjacking)",
    "votes": 12,
    "total_awarded_amount": null,
    "reporter": "mrnull1337",
    "program": "mixmax",
    "program_name": "Mixmax"
  },
  {
    "id": 212629,
    "title": "Gitlab.com is vulnerable to reverse tabnabbing. (#2)",
    "url": "https://hackerone.com/reports/212629",
    "substate": "resolved",
    "severity_rating": "Medium",
    "disclosed": true,
    "disclosed_at": "2017-05-09T19:12:21.392Z",
    "submitted_at": "2017-03-11T18:45:39.677Z",
    "cve_ids": [],
    "cwe": "UI Redressing (Clickjacking)",
    "votes": 8,
    "total_awarded_amount": null,
    "reporter": "edoverflow",
    "program": "gitlab",
    "program_name": "GitLab"
  },
  {
    "id": 213114,
    "title": "Gitlab.com is vulnerable to reverse tabnabbing via AsciiDoc links. (#3)",
    "url": "https://hackerone.com/reports/213114",
    "substate": "resolved",
    "severity_rating": "Medium",
    "disclosed": true,
    "disclosed_at": "2017-05-09T19:11:56.301Z",
    "submitted_at": "2017-03-13T16:17:14.804Z",
    "cve_ids": [],
    "cwe": "UI Redressing (Clickjacking)",
    "votes": 5,
    "total_awarded_amount": null,
    "reporter": "edoverflow",
    "program": "gitlab",
    "program_name": "GitLab"
  },
  {
    "id": 140392,
    "title": "CJ vulnerability in subdomain",
    "url": "https://hackerone.com/reports/140392",
    "substate": "resolved",
    "severity_rating": null,
    "disclosed": true,
    "disclosed_at": "2016-06-09T05:23:38.169Z",
    "submitted_at": "2016-05-23T00:01:53.190Z",
    "cve_ids": [],
    "cwe": "UI Redressing (Clickjacking)",
    "votes": 4,
    "total_awarded_amount": null,
    "reporter": "0x0ameer",
    "program": "deriv",
    "program_name": "Deriv.com"
  },
  {
    "id": 103178,
    "title": "Attack User Privacy Settings - X-Frame-Options missing on m.imgur.com/user/username/settings",
    "url": "https://hackerone.com/reports/103178",
    "substate": "resolved",
    "severity_rating": null,
    "disclosed": true,
    "disclosed_at": "2016-05-04T04:13:46.364Z",
    "submitted_at": "2015-12-03T08:43:34.794Z",
    "cve_ids": [],
    "cwe": "UI Redressing (Clickjacking)",
    "votes": 1,
    "total_awarded_amount": null,
    "reporter": "kasser",
    "program": "imgur",
    "program_name": "Imgur"
  },
  {
    "id": 119828,
    "title": "Found clickjacking vulnerability",
    "url": "https://hackerone.com/reports/119828",
    "substate": "resolved",
    "severity_rating": null,
    "disclosed": true,
    "disclosed_at": "2016-03-23T12:09:45.278Z",
    "submitted_at": "2016-03-01T17:44:37.873Z",
    "cve_ids": [],
    "cwe": "UI Redressing (Clickjacking)",
    "votes": 6,
    "total_awarded_amount": null,
    "reporter": "9-d",
    "program": "leaseweb",
    "program_name": "LeaseWeb"
  },
  {
    "id": 97510,
    "title": "Following a User After Favoriting Actually Follows Another User (related to #95243)",
    "url": "https://hackerone.com/reports/97510",
    "substate": "resolved",
    "severity_rating": null,
    "disclosed": true,
    "disclosed_at": "2015-12-02T17:42:20.929Z",
    "submitted_at": "2015-11-03T21:43:56.140Z",
    "cve_ids": [],
    "cwe": "UI Redressing (Clickjacking)",
    "votes": 1,
    "total_awarded_amount": 280,
    "reporter": "ericr",
    "program": "x",
    "program_name": "X / xAI"
  }
]